cloudgenix_serial_report
