Metadata-Version: 2.1
Name: cloudgenix-serial-report
Version: 1.0.2
Summary: Utility to dump all CloudGenix network serial information to an .XLSX file.
Home-page: https://github.com/ebob9/cloudgenix_serial_report
Author: Aaron Edwards
Author-email: cloudgenix_serial_report@ebob9.com
License: MIT
Platform: UNKNOWN
Classifier: Development Status :: 5 - Production/Stable
Classifier: Intended Audience :: Developers
Classifier: License :: OSI Approved :: MIT License
Classifier: Programming Language :: Python :: 2.7
Classifier: Programming Language :: Python :: 3
